hermes_core/__init__.py
hermes_core/hermes_core.cpython-312-darwin.so
hermes_core_python-1.0.2.dist-info/METADATA
hermes_core_python-1.0.2.dist-info/WHEEL
hermes_core_python-1.0.2.dist-info/RECORD
