Metadata-Version: 2.4
Name: hermes-core-python
Version: 1.0.2
Classifier: Development Status :: 4 - Beta
Classifier: Intended Audience :: Developers
Classifier: License :: OSI Approved :: MIT License
Classifier: Programming Language :: Python :: 3
Classifier: Programming Language :: Python :: 3.9
Classifier: Programming Language :: Python :: 3.10
Classifier: Programming Language :: Python :: 3.11
Classifier: Programming Language :: Python :: 3.12
Classifier: Programming Language :: Python :: 3.13
Classifier: Programming Language :: Python :: 3.14
Classifier: Programming Language :: Rust
Classifier: Topic :: Text Processing :: Indexing
Summary: Python bindings for Hermes search engine
Keywords: search,full-text-search,indexing,ir
Home-Page: https://github.com/SpaceFrontiers/hermes
Author: izihawa
License: MIT
Requires-Python: >=3.9
Project-URL: Documentation, https://github.com/SpaceFrontiers/hermes
Project-URL: Homepage, https://github.com/SpaceFrontiers/hermes
Project-URL: Repository, https://github.com/SpaceFrontiers/hermes
